acore_server_metadata/__init__.py
acore_server_metadata/_version.py
acore_server_metadata/api.py
acore_server_metadata/exc.py
acore_server_metadata/logger.py
acore_server_metadata/paths.py
acore_server_metadata/settings.py
acore_server_metadata/utils.py
acore_server_metadata/docs/__init__.py
acore_server_metadata/server/__init__.py
acore_server_metadata/server/api.py
acore_server_metadata/server/server.py
acore_server_metadata/server/server_operation.py
acore_server_metadata/server/server_status.py
acore_server_metadata/tests/__init__.py
acore_server_metadata/tests/helper.py
acore_server_metadata/tests/mock_aws.py
acore_server_metadata/vendor/__init__.py
acore_server_metadata/vendor/hashes.py
acore_server_metadata/vendor/pytest_cov_helper.py
acore_server_metadata-1.1.1.dist-info/AUTHORS.rst
acore_server_metadata-1.1.1.dist-info/LICENSE.txt
acore_server_metadata-1.1.1.dist-info/METADATA
acore_server_metadata-1.1.1.dist-info/WHEEL
acore_server_metadata-1.1.1.dist-info/top_level.txt
acore_server_metadata-1.1.1.dist-info/RECORD
